updatedns
