Metadata-Version: 2.1
Name: updatedns
Version: 0.7.3
Summary: Command-Line Cloud DNS utility
Home-page: https://shaw.cx/updatedns
Author: Matthew Shaw
Author-email: mshaw.cx@gmail.com
License: MIT
Platform: UNKNOWN
Classifier: Environment :: Console
Classifier: License :: OSI Approved :: MIT License
